setup.py
supra_dist/Binomialdistribution.py
supra_dist/Gaussiandistribution.py
supra_dist/Generaldistribution.py
supra_dist/__init__.py
supra_dist.egg-info/PKG-INFO
supra_dist.egg-info/SOURCES.txt
supra_dist.egg-info/dependency_links.txt
supra_dist.egg-info/not-zip-safe
supra_dist.egg-info/top_level.txt